fmapip/__init__.py
fmapip/bot.py
fmapip/message.py
fmapip-1.0.0.dist-info/licenses/LICENSE
fmapip-1.0.0.dist-info/METADATA
fmapip-1.0.0.dist-info/WHEEL
fmapip-1.0.0.dist-info/top_level.txt
fmapip-1.0.0.dist-info/RECORD
