Metadata-Version: 2.4
Name: fmapip
Version: 1.0.0
Summary: FlorestMessangerAPIPlus
Author: hpasus8
License-Expression: MIT
Project-URL: Homepage, https://florestmsgs-florestdev4185.amvera.io/api_docs/python/plus
Keywords: fmapi,florest,florestmessanger,florestmessangerapi,fmapi+,florestmessanger+,florestmessangerplus
Classifier: Programming Language :: Python :: 3
Classifier: Programming Language :: Python :: 3.10
Classifier: Programming Language :: Python :: 3.11
Classifier: Programming Language :: Python :: 3.12
Classifier: Programming Language :: Python :: 3.13
Requires-Python: >=3.10
License-File: LICENSE
Requires-Dist: florestmessangerapi
Dynamic: license-file
